LICENSE.txt
MANIFEST.in
README.md
ez_setup.py
setup.cfg
setup.py
impala/__init__.py
impala/_thrift_api.py
impala/compat.py
impala/datatypes.py
impala/dbapi.py
impala/error.py
impala/hiveserver2.py
impala/interface.py
impala/sasl_compat.py
impala/sqlalchemy.py
impala/util.py
impala/_thrift_gen/__init__.py
impala/_thrift_gen/ExecStats/__init__.py
impala/_thrift_gen/ExecStats/constants.py
impala/_thrift_gen/ExecStats/ttypes.py
impala/_thrift_gen/ImpalaService/ImpalaHiveServer2Service.py
impala/_thrift_gen/ImpalaService/ImpalaService.py
impala/_thrift_gen/ImpalaService/__init__.py
impala/_thrift_gen/ImpalaService/constants.py
impala/_thrift_gen/ImpalaService/ttypes.py
impala/_thrift_gen/Status/__init__.py
impala/_thrift_gen/Status/constants.py
impala/_thrift_gen/Status/ttypes.py
impala/_thrift_gen/TCLIService/TCLIService.py
impala/_thrift_gen/TCLIService/__init__.py
impala/_thrift_gen/TCLIService/constants.py
impala/_thrift_gen/TCLIService/ttypes.py
impala/_thrift_gen/Types/__init__.py
impala/_thrift_gen/Types/constants.py
impala/_thrift_gen/Types/ttypes.py
impala/_thrift_gen/beeswax/BeeswaxService.py
impala/_thrift_gen/beeswax/__init__.py
impala/_thrift_gen/beeswax/constants.py
impala/_thrift_gen/beeswax/ttypes.py
impala/_thrift_gen/fb303/FacebookService.py
impala/_thrift_gen/fb303/__init__.py
impala/_thrift_gen/fb303/constants.py
impala/_thrift_gen/fb303/ttypes.py
impala/_thrift_gen/hive_metastore/ThriftHiveMetastore.py
impala/_thrift_gen/hive_metastore/__init__.py
impala/_thrift_gen/hive_metastore/constants.py
impala/_thrift_gen/hive_metastore/ttypes.py
impala/tests/__init__.py
impala/tests/_dbapi20_tests.py
impala/tests/compat.py
impala/tests/conftest.py
impala/tests/test_data_types.py
impala/tests/test_dbapi_compliance.py
impala/tests/test_dbapi_connect.py
impala/tests/test_hive.py
impala/tests/test_hive_dict_cursor.py
impala/tests/test_query_parameters.py
impala/tests/test_sqlalchemy.py
impala/tests/util.py
impala/thrift/ExecStats.thrift
ym_impyla.egg-info/PKG-INFO
ym_impyla.egg-info/SOURCES.txt
ym_impyla.egg-info/dependency_links.txt
ym_impyla.egg-info/entry_points.txt
ym_impyla.egg-info/not-zip-safe
ym_impyla.egg-info/requires.txt
ym_impyla.egg-info/top_level.txt