Metadata-Version: 1.1
Name: ym-impyla
Version: 0.14.0
Summary: Python client for the Impala distributed query engine
Home-page: https://github.com/yimian/impyla
Author: Wes McKinney
Author-email: wes.mckinney@twosigma.com
License: Apache License, Version 2.0
Keywords: cloudera impala python hadoop sql hdfs mpp spark pydata pandas distributed db api pep 249 hive hiveserver2 hs2
Platform: UNKNOWN
Classifier: Programming Language :: Python :: 2
Classifier: Programming Language :: Python :: 2.6
Classifier: Programming Language :: Python :: 2.7
Classifier: Programming Language :: Python :: 3
Classifier: Programming Language :: Python :: 3.4
Classifier: Programming Language :: Python :: 3.5
